[{"name":"name1","surname":"surname1","login":"login1"},{"name":"name2","surname":"surname2","login":"login2"},{"name":"name3","surname":"surname3","login":"login3"},{"name":"name4","surname":"surname4","login":"login4"},{"name":"name5","surname":"surname5","login":"login5"},{"name":"name6","surname":"surname6","login":"login6"},{"name":"name7","surname":"surname7","login":"login7"},{"name":"name8","surname":"surname8","login":"login8"},{"name":"name9","surname":"surname9","login":"login9"},{"name":"name10","surname":"surname10","login":"login10"},{"name":"name11","surname":"surname11","login":"login11"},{"name":"name12","surname":"surname12","login":"login12"},{"name":"name13","surname":"surname13","login":"login13"},{"name":"name14","surname":"surname14","login":"login14"},{"name":"name15","surname":"surname15","login":"login15"},{"name":"name16","surname":"surname16","login":"login16"},{"name":"name17","surname":"surname17","login":"login17"},{"name":"name18","surname":"surname18","login":"login18"},{"name":"name19","surname":"surname19","login":"login19"},{"name":"name20","surname":"surname20","login":"login20"},{"name":"name21","surname":"surname21","login":"login21"},{"name":"name22","surname":"surname22","login":"login22"},{"name":"name23","surname":"surname23","login":"login23"},{"name":"name24","surname":"surname24","login":"login24"},{"name":"name25","surname":"surname25","login":"login25"},{"name":"name26","surname":"surname26","login":"login26"},{"name":"name27","surname":"surname27","login":"login27"},{"name":"name28","surname":"surname28","login":"login28"},{"name":"name29","surname":"surname29","login":"login29"},{"name":"name30","surname":"surname30","login":"login30"},{"name":"name31","surname":"surname31","login":"login31"},{"name":"name32","surname":"surname32","login":"login32"},{"name":"name33","surname":"surname33","login":"login33"},{"name":"name34","surname":"surname34","login":"login34"},{"name":"name35","surname":"surname35","login":"login35"},{"name":"name36","surname":"surname36","login":"login36"},{"name":"name37","surname":"surname37","login":"login37"},{"name":"name38","surname":"surname38","login":"login38"},{"name":"name39","surname":"surname39","login":"login39"},{"name":"name40","surname":"surname40","login":"login40"},{"name":"name41","surname":"surname41","login":"login41"},{"name":"name42","surname":"surname42","login":"login42"},{"name":"name43","surname":"surname43","login":"login43"},{"name":"name44","surname":"surname44","login":"login44"},{"name":"name45","surname":"surname45","login":"login45"},{"name":"name46","surname":"surname46","login":"login46"},{"name":"name47","surname":"surname47","login":"login47"},{"name":"name48","surname":"surname48","login":"login48"},{"name":"name49","surname":"surname49","login":"login49"},{"name":"name50","surname":"surname50","login":"login50"},{"name":"name51","surname":"surname51","login":"login51"},{"name":"name52","surname":"surname52","login":"login52"},{"name":"name53","surname":"surname53","login":"login53"},{"name":"name54","surname":"surname54","login":"login54"},{"name":"name55","surname":"surname55","login":"login55"},{"name":"name56","surname":"surname56","login":"login56"},{"name":"name57","surname":"surname57","login":"login57"},{"name":"name58","surname":"surname58","login":"login58"},{"name":"name59","surname":"surname59","login":"login59"},{"name":"name60","surname":"surname60","login":"login60"},{"name":"name61","surname":"surname61","login":"login61"},{"name":"name62","surname":"surname62","login":"login62"},{"name":"name63","surname":"surname63","login":"login63"},{"name":"name64","surname":"surname64","login":"login64"},{"name":"name65","surname":"surname65","login":"login65"},{"name":"name66","surname":"surname66","login":"login66"},{"name":"name67","surname":"surname67","login":"login67"},{"name":"name68","surname":"surname68","login":"login68"},{"name":"name69","surname":"surname69","login":"login69"},{"name":"name70","surname":"surname70","login":"login70"},{"name":"name71","surname":"surname71","login":"login71"},{"name":"name72","surname":"surname72","login":"login72"},{"name":"name73","surname":"surname73","login":"login73"},{"name":"name74","surname":"surname74","login":"login74"},{"name":"name75","surname":"surname75","login":"login75"},{"name":"name76","surname":"surname76","login":"login76"},{"name":"name77","surname":"surname77","login":"login77"},{"name":"name78","surname":"surname78","login":"login78"},{"name":"name79","surname":"surname79","login":"login79"},{"name":"name80","surname":"surname80","login":"login80"},{"name":"name81","surname":"surname81","login":"login81"},{"name":"name82","surname":"surname82","login":"login82"},{"name":"name83","surname":"surname83","login":"login83"},{"name":"name84","surname":"surname84","login":"login84"},{"name":"name85","surname":"surname85","login":"login85"},{"name":"name86","surname":"surname86","login":"login86"},{"name":"name87","surname":"surname87","login":"login87"},{"name":"name88","surname":"surname88","login":"login88"},{"name":"name89","surname":"surname89","login":"login89"},{"name":"name90","surname":"surname90","login":"login90"},{"name":"name91","surname":"surname91","login":"login91"},{"name":"name92","surname":"surname92","login":"login92"},{"name":"name93","surname":"surname93","login":"login93"},{"name":"name94","surname":"surname94","login":"login94"},{"name":"name95","surname":"surname95","login":"login95"},{"name":"name96","surname":"surname96","login":"login96"},{"name":"name97","surname":"surname97","login":"login97"},{"name":"name98","surname":"surname98","login":"login98"},{"name":"name99","surname":"surname99","login":"login99"},{"name":"name100","surname":"surname100","login":"login100"},{"name":"name101","surname":"surname101","login":"login101"},{"name":"name102","surname":"surname102","login":"login102"},{"name":"name103","surname":"surname103","login":"login103"},{"name":"name104","surname":"surname104","login":"login104"},{"name":"name105","surname":"surname105","login":"login105"},{"name":"name106","surname":"surname106","login":"login106"},{"name":"name107","surname":"surname107","login":"login107"},{"name":"name108","surname":"surname108","login":"login108"},{"name":"name109","surname":"surname109","login":"login109"},{"name":"name110","surname":"surname110","login":"login110"},{"name":"name111","surname":"surname111","login":"login111"},{"name":"name112","surname":"surname112","login":"login112"},{"name":"name113","surname":"surname113","login":"login113"},{"name":"name114","surname":"surname114","login":"login114"},{"name":"name115","surname":"surname115","login":"login115"},{"name":"name116","surname":"surname116","login":"login116"},{"name":"name117","surname":"surname117","login":"login117"},{"name":"name118","surname":"surname118","login":"login118"},{"name":"name119","surname":"surname119","login":"login119"},{"name":"name120","surname":"surname120","login":"login120"},{"name":"name121","surname":"surname121","login":"login121"},{"name":"name122","surname":"surname122","login":"login122"},{"name":"name123","surname":"surname123","login":"login123"},{"name":"name124","surname":"surname124","login":"login124"},{"name":"name125","surname":"surname125","login":"login125"},{"name":"name126","surname":"surname126","login":"login126"},{"name":"name127","surname":"surname127","login":"login127"},{"name":"name128","surname":"surname128","login":"login128"},{"name":"name129","surname":"surname129","login":"login129"},{"name":"name130","surname":"surname130","login":"login130"},{"name":"name131","surname":"surname131","login":"login131"},{"name":"name132","surname":"surname132","login":"login132"},{"name":"name133","surname":"surname133","login":"login133"},{"name":"name134","surname":"surname134","login":"login134"},{"name":"name135","surname":"surname135","login":"login135"},{"name":"name136","surname":"surname136","login":"login136"},{"name":"name137","surname":"surname137","login":"login137"},{"name":"name138","surname":"surname138","login":"login138"},{"name":"name139","surname":"surname139","login":"login139"},{"name":"name140","surname":"surname140","login":"login140"},{"name":"name141","surname":"surname141","login":"login141"},{"name":"name142","surname":"surname142","login":"login142"},{"name":"name143","surname":"surname143","login":"login143"},{"name":"name144","surname":"surname144","login":"login144"},{"name":"name145","surname":"surname145","login":"login145"},{"name":"name146","surname":"surname146","login":"login146"},{"name":"name147","surname":"surname147","login":"login147"},{"name":"name148","surname":"surname148","login":"login148"},{"name":"name149","surname":"surname149","login":"login149"},{"name":"name150","surname":"surname150","login":"login150"},{"name":"name151","surname":"surname151","login":"login151"},{"name":"name152","surname":"surname152","login":"login152"},{"name":"name153","surname":"surname153","login":"login153"},{"name":"name154","surname":"surname154","login":"login154"},{"name":"name155","surname":"surname155","login":"login155"},{"name":"name156","surname":"surname156","login":"login156"},{"name":"name157","surname":"surname157","login":"login157"},{"name":"name158","surname":"surname158","login":"login158"},{"name":"name159","surname":"surname159","login":"login159"},{"name":"name160","surname":"surname160","login":"login160"},{"name":"name161","surname":"surname161","login":"login161"},{"name":"name162","surname":"surname162","login":"login162"},{"name":"name163","surname":"surname163","login":"login163"},{"name":"name164","surname":"surname164","login":"login164"},{"name":"name165","surname":"surname165","login":"login165"},{"name":"name166","surname":"surname166","login":"login166"},{"name":"name167","surname":"surname167","login":"login167"},{"name":"name168","surname":"surname168","login":"login168"},{"name":"name169","surname":"surname169","login":"login169"},{"name":"name170","surname":"surname170","login":"login170"},{"name":"name171","surname":"surname171","login":"login171"},{"name":"name172","surname":"surname172","login":"login172"},{"name":"name173","surname":"surname173","login":"login173"},{"name":"name174","surname":"surname174","login":"login174"},{"name":"name175","surname":"surname175","login":"login175"},{"name":"name176","surname":"surname176","login":"login176"},{"name":"name177","surname":"surname177","login":"login177"},{"name":"name178","surname":"surname178","login":"login178"},{"name":"name179","surname":"surname179","login":"login179"},{"name":"name180","surname":"surname180","login":"login180"},{"name":"name181","surname":"surname181","login":"login181"},{"name":"name182","surname":"surname182","login":"login182"},{"name":"name183","surname":"surname183","login":"login183"},{"name":"name184","surname":"surname184","login":"login184"},{"name":"name185","surname":"surname185","login":"login185"},{"name":"name186","surname":"surname186","login":"login186"},{"name":"name187","surname":"surname187","login":"login187"},{"name":"name188","surname":"surname188","login":"login188"},{"name":"name189","surname":"surname189","login":"login189"},{"name":"name190","surname":"surname190","login":"login190"},{"name":"name191","surname":"surname191","login":"login191"},{"name":"name192","surname":"surname192","login":"login192"},{"name":"name193","surname":"surname193","login":"login193"},{"name":"name194","surname":"surname194","login":"login194"},{"name":"name195","surname":"surname195","login":"login195"},{"name":"name196","surname":"surname196","login":"login196"},{"name":"name197","surname":"surname197","login":"login197"},{"name":"name198","surname":"surname198","login":"login198"},{"name":"name199","surname":"surname199","login":"login199"},{"name":"name200","surname":"surname200","login":"login200"},{"name":"name201","surname":"surname201","login":"login201"},{"name":"name202","surname":"surname202","login":"login202"},{"name":"name203","surname":"surname203","login":"login203"},{"name":"name204","surname":"surname204","login":"login204"},{"name":"name205","surname":"surname205","login":"login205"},{"name":"name206","surname":"surname206","login":"login206"},{"name":"name207","surname":"surname207","login":"login207"},{"name":"name208","surname":"surname208","login":"login208"},{"name":"name209","surname":"surname209","login":"login209"},{"name":"name210","surname":"surname210","login":"login210"},{"name":"name211","surname":"surname211","login":"login211"},{"name":"name212","surname":"surname212","login":"login212"},{"name":"name213","surname":"surname213","login":"login213"},{"name":"name214","surname":"surname214","login":"login214"},{"name":"name215","surname":"surname215","login":"login215"},{"name":"name216","surname":"surname216","login":"login216"},{"name":"name217","surname":"surname217","login":"login217"},{"name":"name218","surname":"surname218","login":"login218"},{"name":"name219","surname":"surname219","login":"login219"},{"name":"name220","surname":"surname220","login":"login220"},{"name":"name221","surname":"surname221","login":"login221"},{"name":"name222","surname":"surname222","login":"login222"},{"name":"name223","surname":"surname223","login":"login223"},{"name":"name224","surname":"surname224","login":"login224"},{"name":"name225","surname":"surname225","login":"login225"},{"name":"name226","surname":"surname226","login":"login226"},{"name":"name227","surname":"surname227","login":"login227"},{"name":"name228","surname":"surname228","login":"login228"},{"name":"name229","surname":"surname229","login":"login229"},{"name":"name230","surname":"surname230","login":"login230"},{"name":"name231","surname":"surname231","login":"login231"},{"name":"name232","surname":"surname232","login":"login232"},{"name":"name233","surname":"surname233","login":"login233"},{"name":"name234","surname":"surname234","login":"login234"},{"name":"name235","surname":"surname235","login":"login235"},{"name":"name236","surname":"surname236","login":"login236"},{"name":"name237","surname":"surname237","login":"login237"},{"name":"name238","surname":"surname238","login":"login238"},{"name":"name239","surname":"surname239","login":"login239"},{"name":"name240","surname":"surname240","login":"login240"},{"name":"name241","surname":"surname241","login":"login241"},{"name":"name242","surname":"surname242","login":"login242"},{"name":"name243","surname":"surname243","login":"login243"},{"name":"name244","surname":"surname244","login":"login244"},{"name":"name245","surname":"surname245","login":"login245"},{"name":"name246","surname":"surname246","login":"login246"},{"name":"name247","surname":"surname247","login":"login247"},{"name":"name248","surname":"surname248","login":"login248"},{"name":"name249","surname":"surname249","login":"login249"},{"name":"name250","surname":"surname250","login":"login250"},{"name":"name251","surname":"surname251","login":"login251"},{"name":"name252","surname":"surname252","login":"login252"},{"name":"name253","surname":"surname253","login":"login253"},{"name":"name254","surname":"surname254","login":"login254"},{"name":"name255","surname":"surname255","login":"login255"},{"name":"name256","surname":"surname256","login":"login256"},{"name":"name257","surname":"surname257","login":"login257"},{"name":"name258","surname":"surname258","login":"login258"},{"name":"name259","surname":"surname259","login":"login259"},{"name":"name260","surname":"surname260","login":"login260"},{"name":"name261","surname":"surname261","login":"login261"},{"name":"name262","surname":"surname262","login":"login262"},{"name":"name263","surname":"surname263","login":"login263"},{"name":"name264","surname":"surname264","login":"login264"},{"name":"name265","surname":"surname265","login":"login265"},{"name":"name266","surname":"surname266","login":"login266"},{"name":"name267","surname":"surname267","login":"login267"},{"name":"name268","surname":"surname268","login":"login268"},{"name":"name269","surname":"surname269","login":"login269"},{"name":"name270","surname":"surname270","login":"login270"},{"name":"name271","surname":"surname271","login":"login271"},{"name":"name272","surname":"surname272","login":"login272"},{"name":"name273","surname":"surname273","login":"login273"},{"name":"name274","surname":"surname274","login":"login274"},{"name":"name275","surname":"surname275","login":"login275"},{"name":"name276","surname":"surname276","login":"login276"},{"name":"name277","surname":"surname277","login":"login277"},{"name":"name278","surname":"surname278","login":"login278"},{"name":"name279","surname":"surname279","login":"login279"},{"name":"name280","surname":"surname280","login":"login280"},{"name":"name281","surname":"surname281","login":"login281"},{"name":"name282","surname":"surname282","login":"login282"},{"name":"name283","surname":"surname283","login":"login283"},{"name":"name284","surname":"surname284","login":"login284"},{"name":"name285","surname":"surname285","login":"login285"},{"name":"name286","surname":"surname286","login":"login286"},{"name":"name287","surname":"surname287","login":"login287"},{"name":"name288","surname":"surname288","login":"login288"},{"name":"name289","surname":"surname289","login":"login289"},{"name":"name290","surname":"surname290","login":"login290"},{"name":"name291","surname":"surname291","login":"login291"},{"name":"name292","surname":"surname292","login":"login292"},{"name":"name293","surname":"surname293","login":"login293"},{"name":"name294","surname":"surname294","login":"login294"},{"name":"name295","surname":"surname295","login":"login295"},{"name":"name296","surname":"surname296","login":"login296"},{"name":"name297","surname":"surname297","login":"login297"},{"name":"name298","surname":"surname298","login":"login298"},{"name":"name299","surname":"surname299","login":"login299"},{"name":"name300","surname":"surname300","login":"login300"},{"name":"name301","surname":"surname301","login":"login301"},{"name":"name302","surname":"surname302","login":"login302"},{"name":"name303","surname":"surname303","login":"login303"},{"name":"name304","surname":"surname304","login":"login304"},{"name":"name305","surname":"surname305","login":"login305"},{"name":"name306","surname":"surname306","login":"login306"},{"name":"name307","surname":"surname307","login":"login307"},{"name":"name308","surname":"surname308","login":"login308"},{"name":"name309","surname":"surname309","login":"login309"},{"name":"name310","surname":"surname310","login":"login310"},{"name":"name311","surname":"surname311","login":"login311"},{"name":"name312","surname":"surname312","login":"login312"},{"name":"name313","surname":"surname313","login":"login313"},{"name":"name314","surname":"surname314","login":"login314"},{"name":"name315","surname":"surname315","login":"login315"},{"name":"name316","surname":"surname316","login":"login316"},{"name":"name317","surname":"surname317","login":"login317"},{"name":"name318","surname":"surname318","login":"login318"},{"name":"name319","surname":"surname319","login":"login319"},{"name":"name320","surname":"surname320","login":"login320"},{"name":"name321","surname":"surname321","login":"login321"},{"name":"name322","surname":"surname322","login":"login322"},{"name":"name323","surname":"surname323","login":"login323"},{"name":"name324","surname":"surname324","login":"login324"},{"name":"name325","surname":"surname325","login":"login325"},{"name":"name326","surname":"surname326","login":"login326"},{"name":"name327","surname":"surname327","login":"login327"},{"name":"name328","surname":"surname328","login":"login328"},{"name":"name329","surname":"surname329","login":"login329"},{"name":"name330","surname":"surname330","login":"login330"},{"name":"name331","surname":"surname331","login":"login331"},{"name":"name332","surname":"surname332","login":"login332"},{"name":"name333","surname":"surname333","login":"login333"},{"name":"name334","surname":"surname334","login":"login334"},{"name":"name335","surname":"surname335","login":"login335"},{"name":"name336","surname":"surname336","login":"login336"},{"name":"name337","surname":"surname337","login":"login337"},{"name":"name338","surname":"surname338","login":"login338"},{"name":"name339","surname":"surname339","login":"login339"},{"name":"name340","surname":"surname340","login":"login340"},{"name":"name341","surname":"surname341","login":"login341"},{"name":"name342","surname":"surname342","login":"login342"},{"name":"name343","surname":"surname343","login":"login343"},{"name":"name344","surname":"surname344","login":"login344"},{"name":"name345","surname":"surname345","login":"login345"},{"name":"name346","surname":"surname346","login":"login346"},{"name":"name347","surname":"surname347","login":"login347"},{"name":"name348","surname":"surname348","login":"login348"},{"name":"name349","surname":"surname349","login":"login349"},{"name":"name350","surname":"surname350","login":"login350"},{"name":"name351","surname":"surname351","login":"login351"},{"name":"name352","surname":"surname352","login":"login352"},{"name":"name353","surname":"surname353","login":"login353"},{"name":"name354","surname":"surname354","login":"login354"},{"name":"name355","surname":"surname355","login":"login355"},{"name":"name356","surname":"surname356","login":"login356"},{"name":"name357","surname":"surname357","login":"login357"},{"name":"name358","surname":"surname358","login":"login358"},{"name":"name359","surname":"surname359","login":"login359"},{"name":"name360","surname":"surname360","login":"login360"},{"name":"name361","surname":"surname361","login":"login361"},{"name":"name362","surname":"surname362","login":"login362"},{"name":"name363","surname":"surname363","login":"login363"},{"name":"name364","surname":"surname364","login":"login364"},{"name":"name365","surname":"surname365","login":"login365"},{"name":"name366","surname":"surname366","login":"login366"},{"name":"name367","surname":"surname367","login":"login367"},{"name":"name368","surname":"surname368","login":"login368"},{"name":"name369","surname":"surname369","login":"login369"},{"name":"name370","surname":"surname370","login":"login370"},{"name":"name371","surname":"surname371","login":"login371"},{"name":"name372","surname":"surname372","login":"login372"},{"name":"name373","surname":"surname373","login":"login373"},{"name":"name374","surname":"surname374","login":"login374"},{"name":"name375","surname":"surname375","login":"login375"},{"name":"name376","surname":"surname376","login":"login376"},{"name":"name377","surname":"surname377","login":"login377"},{"name":"name378","surname":"surname378","login":"login378"},{"name":"name379","surname":"surname379","login":"login379"},{"name":"name380","surname":"surname380","login":"login380"},{"name":"name381","surname":"surname381","login":"login381"},{"name":"name382","surname":"surname382","login":"login382"},{"name":"name383","surname":"surname383","login":"login383"},{"name":"name384","surname":"surname384","login":"login384"},{"name":"name385","surname":"surname385","login":"login385"},{"name":"name386","surname":"surname386","login":"login386"},{"name":"name387","surname":"surname387","login":"login387"},{"name":"name388","surname":"surname388","login":"login388"},{"name":"name389","surname":"surname389","login":"login389"},{"name":"name390","surname":"surname390","login":"login390"},{"name":"name391","surname":"surname391","login":"login391"},{"name":"name392","surname":"surname392","login":"login392"},{"name":"name393","surname":"surname393","login":"login393"},{"name":"name394","surname":"surname394","login":"login394"},{"name":"name395","surname":"surname395","login":"login395"},{"name":"name396","surname":"surname396","login":"login396"},{"name":"name397","surname":"surname397","login":"login397"},{"name":"name398","surname":"surname398","login":"login398"},{"name":"name399","surname":"surname399","login":"login399"},{"name":"name400","surname":"surname400","login":"login400"},{"name":"name401","surname":"surname401","login":"login401"},{"name":"name402","surname":"surname402","login":"login402"},{"name":"name403","surname":"surname403","login":"login403"},{"name":"name404","surname":"surname404","login":"login404"},{"name":"name405","surname":"surname405","login":"login405"},{"name":"name406","surname":"surname406","login":"login406"},{"name":"name407","surname":"surname407","login":"login407"},{"name":"name408","surname":"surname408","login":"login408"},{"name":"name409","surname":"surname409","login":"login409"},{"name":"name410","surname":"surname410","login":"login410"},{"name":"name411","surname":"surname411","login":"login411"},{"name":"name412","surname":"surname412","login":"login412"},{"name":"name413","surname":"surname413","login":"login413"},{"name":"name414","surname":"surname414","login":"login414"},{"name":"name415","surname":"surname415","login":"login415"},{"name":"name416","surname":"surname416","login":"login416"},{"name":"name417","surname":"surname417","login":"login417"},{"name":"name418","surname":"surname418","login":"login418"},{"name":"name419","surname":"surname419","login":"login419"},{"name":"name420","surname":"surname420","login":"login420"},{"name":"name421","surname":"surname421","login":"login421"},{"name":"name422","surname":"surname422","login":"login422"},{"name":"name423","surname":"surname423","login":"login423"},{"name":"name424","surname":"surname424","login":"login424"},{"name":"name425","surname":"surname425","login":"login425"},{"name":"name426","surname":"surname426","login":"login426"},{"name":"name427","surname":"surname427","login":"login427"},{"name":"name428","surname":"surname428","login":"login428"},{"name":"name429","surname":"surname429","login":"login429"},{"name":"name430","surname":"surname430","login":"login430"},{"name":"name431","surname":"surname431","login":"login431"},{"name":"name432","surname":"surname432","login":"login432"},{"name":"name433","surname":"surname433","login":"login433"},{"name":"name434","surname":"surname434","login":"login434"},{"name":"name435","surname":"surname435","login":"login435"},{"name":"name436","surname":"surname436","login":"login436"},{"name":"name437","surname":"surname437","login":"login437"},{"name":"name438","surname":"surname438","login":"login438"},{"name":"name439","surname":"surname439","login":"login439"},{"name":"name440","surname":"surname440","login":"login440"},{"name":"name441","surname":"surname441","login":"login441"},{"name":"name442","surname":"surname442","login":"login442"},{"name":"name443","surname":"surname443","login":"login443"},{"name":"name444","surname":"surname444","login":"login444"},{"name":"name445","surname":"surname445","login":"login445"},{"name":"name446","surname":"surname446","login":"login446"},{"name":"name447","surname":"surname447","login":"login447"},{"name":"name448","surname":"surname448","login":"login448"},{"name":"name449","surname":"surname449","login":"login449"},{"name":"name450","surname":"surname450","login":"login450"},{"name":"name451","surname":"surname451","login":"login451"},{"name":"name452","surname":"surname452","login":"login452"},{"name":"name453","surname":"surname453","login":"login453"},{"name":"name454","surname":"surname454","login":"login454"},{"name":"name455","surname":"surname455","login":"login455"},{"name":"name456","surname":"surname456","login":"login456"},{"name":"name457","surname":"surname457","login":"login457"},{"name":"name458","surname":"surname458","login":"login458"},{"name":"name459","surname":"surname459","login":"login459"},{"name":"name460","surname":"surname460","login":"login460"},{"name":"name461","surname":"surname461","login":"login461"},{"name":"name462","surname":"surname462","login":"login462"},{"name":"name463","surname":"surname463","login":"login463"},{"name":"name464","surname":"surname464","login":"login464"},{"name":"name465","surname":"surname465","login":"login465"},{"name":"name466","surname":"surname466","login":"login466"},{"name":"name467","surname":"surname467","login":"login467"},{"name":"name468","surname":"surname468","login":"login468"},{"name":"name469","surname":"surname469","login":"login469"},{"name":"name470","surname":"surname470","login":"login470"},{"name":"name471","surname":"surname471","login":"login471"},{"name":"name472","surname":"surname472","login":"login472"},{"name":"name473","surname":"surname473","login":"login473"},{"name":"name474","surname":"surname474","login":"login474"},{"name":"name475","surname":"surname475","login":"login475"},{"name":"name476","surname":"surname476","login":"login476"},{"name":"name477","surname":"surname477","login":"login477"},{"name":"name478","surname":"surname478","login":"login478"},{"name":"name479","surname":"surname479","login":"login479"},{"name":"name480","surname":"surname480","login":"login480"},{"name":"name481","surname":"surname481","login":"login481"},{"name":"name482","surname":"surname482","login":"login482"},{"name":"name483","surname":"surname483","login":"login483"},{"name":"name484","surname":"surname484","login":"login484"},{"name":"name485","surname":"surname485","login":"login485"},{"name":"name486","surname":"surname486","login":"login486"},{"name":"name487","surname":"surname487","login":"login487"},{"name":"name488","surname":"surname488","login":"login488"},{"name":"name489","surname":"surname489","login":"login489"},{"name":"name490","surname":"surname490","login":"login490"},{"name":"name491","surname":"surname491","login":"login491"},{"name":"name492","surname":"surname492","login":"login492"},{"name":"name493","surname":"surname493","login":"login493"},{"name":"name494","surname":"surname494","login":"login494"},{"name":"name495","surname":"surname495","login":"login495"},{"name":"name496","surname":"surname496","login":"login496"},{"name":"name497","surname":"surname497","login":"login497"},{"name":"name498","surname":"surname498","login":"login498"},{"name":"name499","surname":"surname499","login":"login499"},{"name":"name500","surname":"surname500","login":"login500"}]